ezplotly/__init__.py
ezplotly/ezplotly.py
ezplotly/settings.py
ezplotly_bio/__init__.py
ezplotly_bio/ezplotly_bio.py
yayrocs/__init__.py
yayrocs/yayrocs.py
ezplotly-0.1.3.0.8.1.dist-info/METADATA
ezplotly-0.1.3.0.8.1.dist-info/WHEEL
ezplotly-0.1.3.0.8.1.dist-info/licenses/LICENSE.txt
ezplotly-0.1.3.0.8.1.dist-info/RECORD
