Metadata-Version: 2.1
Name: ezplotly
Version: 0.1.3.0.8.1
Summary: An easy wrapper for making Plotly plots in Jupyter notebooks
Project-URL: Homepage, https://github.com/prateekt/ezplotly
Project-URL: Bug Tracker, https://github.com/prateekt/ezplotly/issues
Author-email: Prateek Tandon <prateek1.tandon@gmail.com>
License-Expression: MIT
License-File: LICENSE.txt
Classifier: License :: OSI Approved :: MIT License
Classifier: Operating System :: OS Independent
Classifier: Programming Language :: Python :: 3
Requires-Python: >=3.11.4
Requires-Dist: black[jupyter]
Requires-Dist: hatch
Requires-Dist: jupyter
Requires-Dist: kaleido
Requires-Dist: numpy
Requires-Dist: pandas
Requires-Dist: plotly
Requires-Dist: scikit-learn
Requires-Dist: scipy
